jupyterlab_copy_to_recent/__init__.py
jupyterlab_copy_to_recent/_version.py
jupyterlab_copy_to_recent-0.2.1.data/data/share/jupyter/labextensions/jupyterlab-copy-to-recent/package.json
jupyterlab_copy_to_recent-0.2.1.data/data/share/jupyter/labextensions/jupyterlab-copy-to-recent/static/728.9ce17da43c2969edf252.js
jupyterlab_copy_to_recent-0.2.1.data/data/share/jupyter/labextensions/jupyterlab-copy-to-recent/static/890.bc6319e8d867b598a16e.js
jupyterlab_copy_to_recent-0.2.1.data/data/share/jupyter/labextensions/jupyterlab-copy-to-recent/static/remoteEntry.028792d49920be3f6703.js
jupyterlab_copy_to_recent-0.2.1.data/data/share/jupyter/labextensions/jupyterlab-copy-to-recent/static/style.js
jupyterlab_copy_to_recent-0.2.1.data/data/share/jupyter/labextensions/jupyterlab-copy-to-recent/static/third-party-licenses.json
jupyterlab_copy_to_recent-0.2.1.data/data/share/jupyter/labextensions/jupyterlab-copy-to-recent/install.json
jupyterlab_copy_to_recent-0.2.1.dist-info/METADATA
jupyterlab_copy_to_recent-0.2.1.dist-info/WHEEL
jupyterlab_copy_to_recent-0.2.1.dist-info/licenses/LICENSE
jupyterlab_copy_to_recent-0.2.1.dist-info/RECORD
