Metadata-Version: 2.3
Name: jupyterlab_copy_to_recent
Version: 0.2.1
Dynamic: Keywords
Summary: Quickly copy files to most recently open folders
Project-URL: Homepage, https://github.com/kyle-cochran/jupyterlab-copy-to-recent
Project-URL: Bug Tracker, https://github.com/kyle-cochran/jupyterlab-copy-to-recent/issues
Project-URL: Repository, https://github.com/kyle-cochran/jupyterlab-copy-to-recent.git
Author-email: Kyle Cochran <kyle.ray.cochran@gmail.com>
License: BSD 3-Clause License
License-File: LICENSE
Classifier: Framework :: Jupyter
Classifier: Framework :: Jupyter :: JupyterLab
Classifier: Framework :: Jupyter :: JupyterLab :: 4
Classifier: Framework :: Jupyter :: JupyterLab :: Extensions
Classifier: Framework :: Jupyter :: JupyterLab :: Extensions :: Prebuilt
Classifier: License :: OSI Approved :: BSD License
Classifier: Programming Language :: Python
Classifier: Programming Language :: Python :: 3
Classifier: Programming Language :: Python :: 3.8
Classifier: Programming Language :: Python :: 3.9
Classifier: Programming Language :: Python :: 3.10
Classifier: Programming Language :: Python :: 3.11
Classifier: Programming Language :: Python :: 3.12
Requires-Python: >=3.8
